AnarchKeyClient.py
__init__.py
anarchkeyclient-1.2.1.dist-info/licenses/LICENSE
anarchkeyclient-1.2.1.dist-info/METADATA
anarchkeyclient-1.2.1.dist-info/WHEEL
anarchkeyclient-1.2.1.dist-info/entry_points.txt
anarchkeyclient-1.2.1.dist-info/top_level.txt
anarchkeyclient-1.2.1.dist-info/RECORD
