Metadata-Version: 2.4
Name: AnarchKeyClient
Version: 1.2.1
Summary: A Client package to connect and retrieve api keys from vault serivce called AnarchKey
Author-email: AkiTheMemeGod <k.akashkumar@gmail.com>
Project-URL: Homepage, https://github.com/AkiTheMemeGod/AnarchKey_PyPi_Package
Project-URL: Bug Tracker, https://github.com/AkiTheMemeGod/AnarchKey_PyPi_Package/issues
Classifier: Programming Language :: Python :: 3
Classifier: License :: OSI Approved :: MIT License
Classifier: Operating System :: OS Independent
Requires-Python: >=3.7
License-File: LICENSE
Requires-Dist: requests<4.0.0,>=2.31.0
Dynamic: license-file
